AUTHORS
COPYING
INSTALL
MANIFEST.in
README
ROADMAP
build.conf
setup.py
docs/QuickRefManual
yaposib/Binding.cpp
yaposib/CArrays.cpp
yaposib/CArrays.hpp
yaposib/Col.cpp
yaposib/Col.hpp
yaposib/Obj.cpp
yaposib/Obj.hpp
yaposib/Problem.cpp
yaposib/Problem.hpp
yaposib/Row.cpp
yaposib/Row.hpp
yaposib/__init__.py
yaposib/helpers.py
yaposib/init_normal
yaposib/init_preload
yaposib/preload.py
yaposib.egg-info/PKG-INFO
yaposib.egg-info/SOURCES.txt
yaposib.egg-info/dependency_links.txt
yaposib.egg-info/eager_resources.txt
yaposib.egg-info/entry_points.txt
yaposib.egg-info/top_level.txt
yaposib/test/__init__.py
yaposib/test/test_yaposib.py