Metadata-Version: 1.0
Name: yaposib
Version: 0.2.75
Summary: 
